{
  "version": "0.4.10",
  "flags": {},
  "shapes": [
    {
      "label": "blue cylinder",
      "text": "",
      "points": [
        [
          389.0,
          0.0
        ],
        [
          520.0,
          126.0
        ]
      ],
      "group_id": null,
      "shape_type": "rectangle",
      "flags": {}
    },
    {
      "label": "green cylinder",
      "text": "",
      "points": [
        [
          547.0,
          153.0
        ],
        [
          638.0,
          291.0
        ]
      ],
      "group_id": null,
      "shape_type": "rectangle",
      "flags": {}
    }
  ],
  "imagePath": "frame_00021.jpg",
  "imageData": null,
  "imageHeight": 480,
  "imageWidth": 640
}